logtool/__init__.py
logtool/log_fault_impl.py
logtool/log_wrap.py
logtool/logtime.py
logtool-0.4.post2.dist-info/LICENSE
logtool-0.4.post2.dist-info/METADATA
logtool-0.4.post2.dist-info/WHEEL
logtool-0.4.post2.dist-info/RECORD
