Metadata-Version: 2.1
Name: logtool
Version: 0.4.post2
Summary: Methods and tools that assist logging
Home-page: https://github.com/clearclaw/logtool
License: GPL-3.0-only
Keywords: logging,exceptions,callpoints,call tracing
Author: J C Lawrence
Author-email: claw@kanga.nu
Requires-Python: >=3.7,<4.0
Classifier: License :: OSI Approved :: GNU General Public License v3 (GPLv3)
Classifier: Programming Language :: Python :: 3
Classifier: Programming Language :: Python :: 3.7
Classifier: Programming Language :: Python :: 3.8
Classifier: Programming Language :: Python :: 3.9
Classifier: Programming Language :: Python :: 3.10
Classifier: Programming Language :: Python :: 3.11
Classifier: Programming Language :: Python :: 3.12
Requires-Dist: wrapt (>=1.16.0,<2.0.0)
Project-URL: Repository, https://github.com/clearclaw/logtool
